{"data":{"contest":{"name":"Praktikum Modul 1 - Struktur Data C 2021 / 2022","startTime":"2022-03-07T12:00:00Z","endTime":"2022-03-11T12:00:00Z"},"problems":[{"label":"A","name":"Puskesmas"},{"label":"B","name":"Vice sedang Prima"},{"label":"C","name":"Vice Bermain Angka"},{"label":"D","name":"Si Paling Kebo"},{"label":"E","name":"Pembukaan"},{"label":"F","name":"Sapi betina"}],"teams":[{"id":"6004690","institution":{"name":"Institut Teknologi Sepuluh Nopember"},"name":"Muhammad Ersya Vinorian","problems":[{"problem":{"name":"puskesmas","label":"puskesmas"},"tryCount":6,"pendingCount":0,"isSolved":true,"firstToSolve":false,"time":363},{"problem":{"name":"vice-sedang-prima","label":"vice-sedang-prima"},"tryCount":1,"pendingCount":0,"isSolved":true,"firstToSolve":false,"time":133},{"problem":{"name":"vice-bermain-angka","label":"vice-bermain-angka"},"tryCount":7,"pendingCount":0,"isSolved":true,"firstToSolve":false,"time":1225},{"problem":{"name":"si-paling-kebo","label":"si-paling-kebo"},"tryCount":4,"pendingCount":0,"isSolved":true,"firstToSolve":false,"time":686},{"problem":{"name":"pembukaan","label":"pembukaan"},"tryCount":1,"pendingCount":0,"isSolved":true,"firstToSolve":false,"time":202},{"problem":{"name":"sapi-betina","label":"sapi-betina"},"tryCount":1,"pendingCount":0,"isSolved":true,"firstToSolve":false,"time":239}],"score":{"penalty":2853,"solvedCount":6}},{"id":"13588343","institution":{"name":"Institut Teknologi Sepuluh Nopember"},"name":"Muh. Daffa'","problems":[{"problem":{"name":"puskesmas","label":"puskesmas"},"tryCount":7,"pendingCount":0,"isSolved":true,"firstToSolve":false,"time":1249},{"problem":{"name":"vice-sedang-prima","label":"vice-sedang-prima"},"tryCount":4,"pendingCount":0,"isSolved":true,"firstToSolve":false,"time":81},{"problem":{"name":"vice-bermain-angka","label":"vice-bermain-angka"},"tryCount":8,"pendingCount":0,"isSolved":true,"firstToSolve":false,"time":1211},{"problem":{"name":"si-paling-kebo","label":"si-paling-kebo"},"tryCount":0,"pendingCount":0,"isSolved":false,"firstToSolve":false,"time":null},{"problem":{"name":"pembukaan","label":"pembukaan"},"tryCount":1,"pendingCount":0,"isSolved":true,"firstToSolve":false,"time":120},{"problem":{"name":"sapi-betina","label":"sapi-betina"},"tryCount":1,"pendingCount":0,"isSolved":true,"firstToSolve":false,"time":209}],"score":{"penalty":2876,"solvedCount":5}},{"id":"13663526","institution":{"name":"Institut Teknologi Sepuluh Nopember"},"name":"Frederick Hidayat","problems":[{"problem":{"name":"puskesmas","label":"puskesmas"},"tryCount":10,"pendingCount":0,"isSolved":true,"firstToSolve":false,"time":1230},{"problem":{"name":"vice-sedang-prima","label":"vice-sedang-prima"},"tryCount":4,"pendingCount":0,"isSolved":true,"firstToSolve":false,"time":84},{"problem":{"name":"vice-bermain-angka","label":"vice-bermain-angka"},"tryCount":13,"pendingCount":0,"isSolved":true,"firstToSolve":false,"time":1198},{"problem":{"name":"si-paling-kebo","label":"si-paling-kebo"},"tryCount":2,"pendingCount":0,"isSolved":false,"firstToSolve":false,"time":null},{"problem":{"name":"pembukaan","label":"pembukaan"},"tryCount":1,"pendingCount":0,"isSolved":true,"firstToSolve":false,"time":31},{"problem":{"name":"sapi-betina","label":"sapi-betina"},"tryCount":12,"pendingCount":0,"isSolved":true,"firstToSolve":false,"time":1221}],"score":{"penalty":3775,"solvedCount":5}},{"id":"15612504","institution":{"name":"Institut Teknologi Sepuluh Nopember"},"name":"Clarissa Luna","problems":[{"problem":{"name":"puskesmas","label":"puskesmas"},"tryCount":6,"pendingCount":0,"isSolved":true,"firstToSolve":false,"time":1340},{"problem":{"name":"vice-sedang-prima","label":"vice-sedang-prima"},"tryCount":3,"pendingCount":0,"isSolved":true,"firstToSolve":false,"time":233},{"problem":{"name":"vice-bermain-angka","label":"vice-bermain-angka"},"tryCount":1,"pendingCount":0,"isSolved":true,"firstToSolve":false,"time":1433},{"problem":{"name":"si-paling-kebo","label":"si-paling-kebo"},"tryCount":0,"pendingCount":0,"isSolved":false,"firstToSolve":false,"time":null},{"problem":{"name":"pembukaan","label":"pembukaan"},"tryCount":1,"pendingCount":0,"isSolved":true,"firstToSolve":false,"time":286},{"problem":{"name":"sapi-betina","label":"sapi-betina"},"tryCount":1,"pendingCount":0,"isSolved":true,"firstToSolve":false,"time":1102}],"score":{"penalty":4397,"solvedCount":5}},{"id":"13588331","institution":{"name":"Institut Teknologi Sepuluh Nopember"},"name":"Kevin Nathanael","problems":[{"problem":{"name":"puskesmas","label":"puskesmas"},"tryCount":3,"pendingCount":0,"isSolved":false,"firstToSolve":false,"time":null},{"problem":{"name":"vice-sedang-prima","label":"vice-sedang-prima"},"tryCount":5,"pendingCount":0,"isSolved":true,"firstToSolve":false,"time":41},{"problem":{"name":"vice-bermain-angka","label":"vice-bermain-angka"},"tryCount":3,"pendingCount":0,"isSolved":true,"firstToSolve":false,"time":1161},{"problem":{"name":"si-paling-kebo","label":"si-paling-kebo"},"tryCount":8,"pendingCount":0,"isSolved":false,"firstToSolve":false,"time":null},{"problem":{"name":"pembukaan","label":"pembukaan"},"tryCount":1,"pendingCount":0,"isSolved":true,"firstToSolve":false,"time":108},{"problem":{"name":"sapi-betina","label":"sapi-betina"},"tryCount":1,"pendingCount":0,"isSolved":true,"firstToSolve":false,"time":132}],"score":{"penalty":1445,"solvedCount":4}},{"id":"13091407","institution":{"name":"Institut Teknologi Sepuluh Nopember"},"name":"Alfa Fakhrur Rizal","problems":[{"problem":{"name":"puskesmas","label":"puskesmas"},"tryCount":5,"pendingCount":0,"isSolved":true,"firstToSolve":false,"time":451},{"problem":{"name":"vice-sedang-prima","label":"vice-sedang-prima"},"tryCount":9,"pendingCount":0,"isSolved":true,"firstToSolve":false,"time":722},{"problem":{"name":"vice-bermain-angka","label":"vice-bermain-angka"},"tryCount":0,"pendingCount":0,"isSolved":false,"firstToSolve":false,"time":null},{"problem":{"name":"si-paling-kebo","label":"si-paling-kebo"},"tryCount":0,"pendingCount":0,"isSolved":false,"firstToSolve":false,"time":null},{"problem":{"name":"pembukaan","label":"pembukaan"},"tryCount":1,"pendingCount":0,"isSolved":true,"firstToSolve":false,"time":171},{"problem":{"name":"sapi-betina","label":"sapi-betina"},"tryCount":23,"pendingCount":0,"isSolved":true,"firstToSolve":false,"time":1125}],"score":{"penalty":2481,"solvedCount":4}},{"id":"13588354","institution":{"name":"Institut Teknologi Sepuluh Nopember"},"name":"Hammuda Arsyad","problems":[{"problem":{"name":"puskesmas","label":"puskesmas"},"tryCount":0,"pendingCount":0,"isSolved":false,"firstToSolve":false,"time":null},{"problem":{"name":"vice-sedang-prima","label":"vice-sedang-prima"},"tryCount":1,"pendingCount":0,"isSolved":true,"firstToSolve":false,"time":63},{"problem":{"name":"vice-bermain-angka","label":"vice-bermain-angka"},"tryCount":0,"pendingCount":0,"isSolved":false,"firstToSolve":false,"time":null},{"problem":{"name":"si-paling-kebo","label":"si-paling-kebo"},"tryCount":0,"pendingCount":0,"isSolved":false,"firstToSolve":false,"time":null},{"problem":{"name":"pembukaan","label":"pembukaan"},"tryCount":1,"pendingCount":0,"isSolved":true,"firstToSolve":false,"time":201},{"problem":{"name":"sapi-betina","label":"sapi-betina"},"tryCount":1,"pendingCount":0,"isSolved":true,"firstToSolve":false,"time":787}],"score":{"penalty":1051,"solvedCount":3}},{"id":"13588154","institution":{"name":"Institut Teknologi Sepuluh Nopember"},"name":"Andrian Ang","problems":[{"problem":{"name":"puskesmas","label":"puskesmas"},"tryCount":6,"pendingCount":0,"isSolved":false,"firstToSolve":false,"time":null},{"problem":{"name":"vice-sedang-prima","label":"vice-sedang-prima"},"tryCount":5,"pendingCount":0,"isSolved":true,"firstToSolve":false,"time":81},{"problem":{"name":"vice-bermain-angka","label":"vice-bermain-angka"},"tryCount":4,"pendingCount":0,"isSolved":false,"firstToSolve":false,"time":null},{"problem":{"name":"si-paling-kebo","label":"si-paling-kebo"},"tryCount":0,"pendingCount":0,"isSolved":false,"firstToSolve":false,"time":null},{"problem":{"name":"pembukaan","label":"pembukaan"},"tryCount":1,"pendingCount":0,"isSolved":true,"firstToSolve":false,"time":183},{"problem":{"name":"sapi-betina","label":"sapi-betina"},"tryCount":7,"pendingCount":0,"isSolved":true,"firstToSolve":false,"time":1256}],"score":{"penalty":1524,"solvedCount":3}},{"id":"13663360","institution":{"name":"Institut Teknologi Sepuluh Nopember"},"name":"Daud Dhiya'","problems":[{"problem":{"name":"puskesmas","label":"puskesmas"},"tryCount":7,"pendingCount":0,"isSolved":false,"firstToSolve":false,"time":null},{"problem":{"name":"vice-sedang-prima","label":"vice-sedang-prima"},"tryCount":2,"pendingCount":0,"isSolved":true,"firstToSolve":false,"time":98},{"problem":{"name":"vice-bermain-angka","label":"vice-bermain-angka"},"tryCount":0,"pendingCount":0,"isSolved":false,"firstToSolve":false,"time":null},{"problem":{"name":"si-paling-kebo","label":"si-paling-kebo"},"tryCount":0,"pendingCount":0,"isSolved":false,"firstToSolve":false,"time":null},{"problem":{"name":"pembukaan","label":"pembukaan"},"tryCount":1,"pendingCount":0,"isSolved":true,"firstToSolve":false,"time":134},{"problem":{"name":"sapi-betina","label":"sapi-betina"},"tryCount":6,"pendingCount":0,"isSolved":true,"firstToSolve":false,"time":1327}],"score":{"penalty":1561,"solvedCount":3}},{"id":"13589275","institution":{"name":"Institut Teknologi Sepuluh Nopember"},"name":"Hanun Shaka","problems":[{"problem":{"name":"puskesmas","label":"puskesmas"},"tryCount":0,"pendingCount":0,"isSolved":false,"firstToSolve":false,"time":null},{"problem":{"name":"vice-sedang-prima","label":"vice-sedang-prima"},"tryCount":5,"pendingCount":0,"isSolved":true,"firstToSolve":false,"time":1240},{"problem":{"name":"vice-bermain-angka","label":"vice-bermain-angka"},"tryCount":0,"pendingCount":0,"isSolved":false,"firstToSolve":false,"time":null},{"problem":{"name":"si-paling-kebo","label":"si-paling-kebo"},"tryCount":0,"pendingCount":0,"isSolved":false,"firstToSolve":false,"time":null},{"problem":{"name":"pembukaan","label":"pembukaan"},"tryCount":1,"pendingCount":0,"isSolved":true,"firstToSolve":false,"time":349},{"problem":{"name":"sapi-betina","label":"sapi-betina"},"tryCount":2,"pendingCount":0,"isSolved":true,"firstToSolve":false,"time":265}],"score":{"penalty":1856,"solvedCount":3}},{"id":"13588319","institution":{"name":"Institut Teknologi Sepuluh Nopember"},"name":"Muhammad Rafif Tri Risqullah","problems":[{"problem":{"name":"puskesmas","label":"puskesmas"},"tryCount":4,"pendingCount":0,"isSolved":false,"firstToSolve":false,"time":null},{"problem":{"name":"vice-sedang-prima","label":"vice-sedang-prima"},"tryCount":3,"pendingCount":0,"isSolved":true,"firstToSolve":false,"time":877},{"problem":{"name":"vice-bermain-angka","label":"vice-bermain-angka"},"tryCount":2,"pendingCount":0,"isSolved":true,"firstToSolve":false,"time":1377},{"problem":{"name":"si-paling-kebo","label":"si-paling-kebo"},"tryCount":0,"pendingCount":0,"isSolved":false,"firstToSolve":false,"time":null},{"problem":{"name":"pembukaan","label":"pembukaan"},"tryCount":1,"pendingCount":0,"isSolved":true,"firstToSolve":false,"time":1217},{"problem":{"name":"sapi-betina","label":"sapi-betina"},"tryCount":1,"pendingCount":0,"isSolved":false,"firstToSolve":false,"time":null}],"score":{"penalty":3472,"solvedCount":3}},{"id":"13663320","institution":{"name":"Institut Teknologi Sepuluh Nopember"},"name":"Sony Hermawan","problems":[{"problem":{"name":"puskesmas","label":"puskesmas"},"tryCount":0,"pendingCount":0,"isSolved":false,"firstToSolve":false,"time":null},{"problem":{"name":"vice-sedang-prima","label":"vice-sedang-prima"},"tryCount":2,"pendingCount":0,"isSolved":true,"firstToSolve":false,"time":128},{"problem":{"name":"vice-bermain-angka","label":"vice-bermain-angka"},"tryCount":0,"pendingCount":0,"isSolved":false,"firstToSolve":false,"time":null},{"problem":{"name":"si-paling-kebo","label":"si-paling-kebo"},"tryCount":0,"pendingCount":0,"isSolved":false,"firstToSolve":false,"time":null},{"problem":{"name":"pembukaan","label":"pembukaan"},"tryCount":1,"pendingCount":0,"isSolved":true,"firstToSolve":false,"time":236},{"problem":{"name":"sapi-betina","label":"sapi-betina"},"tryCount":0,"pendingCount":0,"isSolved":false,"firstToSolve":false,"time":null}],"score":{"penalty":365,"solvedCount":2}},{"id":"13588155","institution":{"name":"Institut Teknologi Sepuluh Nopember"},"name":"M Zikri","problems":[{"problem":{"name":"puskesmas","label":"puskesmas"},"tryCount":0,"pendingCount":0,"isSolved":false,"firstToSolve":false,"time":null},{"problem":{"name":"vice-sedang-prima","label":"vice-sedang-prima"},"tryCount":4,"pendingCount":0,"isSolved":true,"firstToSolve":false,"time":122},{"problem":{"name":"vice-bermain-angka","label":"vice-bermain-angka"},"tryCount":0,"pendingCount":0,"isSolved":false,"firstToSolve":false,"time":null},{"problem":{"name":"si-paling-kebo","label":"si-paling-kebo"},"tryCount":0,"pendingCount":0,"isSolved":false,"firstToSolve":false,"time":null},{"problem":{"name":"pembukaan","label":"pembukaan"},"tryCount":1,"pendingCount":0,"isSolved":true,"firstToSolve":false,"time":288},{"problem":{"name":"sapi-betina","label":"sapi-betina"},"tryCount":1,"pendingCount":0,"isSolved":false,"firstToSolve":false,"time":null}],"score":{"penalty":410,"solvedCount":2}},{"id":"13594200","institution":{"name":"Institut Teknologi Sepuluh Nopember"},"name":"Ulima Kaltsum Rizky Hibatullah _","problems":[{"problem":{"name":"puskesmas","label":"puskesmas"},"tryCount":0,"pendingCount":0,"isSolved":false,"firstToSolve":false,"time":null},{"problem":{"name":"vice-sedang-prima","label":"vice-sedang-prima"},"tryCount":1,"pendingCount":0,"isSolved":true,"firstToSolve":false,"time":175},{"problem":{"name":"vice-bermain-angka","label":"vice-bermain-angka"},"tryCount":0,"pendingCount":0,"isSolved":false,"firstToSolve":false,"time":null},{"problem":{"name":"si-paling-kebo","label":"si-paling-kebo"},"tryCount":0,"pendingCount":0,"isSolved":false,"firstToSolve":false,"time":null},{"problem":{"name":"pembukaan","label":"pembukaan"},"tryCount":3,"pendingCount":0,"isSolved":true,"firstToSolve":false,"time":800},{"problem":{"name":"sapi-betina","label":"sapi-betina"},"tryCount":0,"pendingCount":0,"isSolved":false,"firstToSolve":false,"time":null}],"score":{"penalty":975,"solvedCount":2}},{"id":"13663425","institution":{"name":"Institut Teknologi Sepuluh Nopember"},"name":"C_1110_Fadilla Rizky Nurhidayah","problems":[{"problem":{"name":"puskesmas","label":"puskesmas"},"tryCount":0,"pendingCount":0,"isSolved":false,"firstToSolve":false,"time":null},{"problem":{"name":"vice-sedang-prima","label":"vice-sedang-prima"},"tryCount":1,"pendingCount":0,"isSolved":true,"firstToSolve":false,"time":185},{"problem":{"name":"vice-bermain-angka","label":"vice-bermain-angka"},"tryCount":0,"pendingCount":0,"isSolved":false,"firstToSolve":false,"time":null},{"problem":{"name":"si-paling-kebo","label":"si-paling-kebo"},"tryCount":0,"pendingCount":0,"isSolved":false,"firstToSolve":false,"time":null},{"problem":{"name":"pembukaan","label":"pembukaan"},"tryCount":2,"pendingCount":0,"isSolved":true,"firstToSolve":false,"time":874},{"problem":{"name":"sapi-betina","label":"sapi-betina"},"tryCount":0,"pendingCount":0,"isSolved":false,"firstToSolve":false,"time":null}],"score":{"penalty":1060,"solvedCount":2}},{"id":"13663588","institution":{"name":"Institut Teknologi Sepuluh Nopember"},"name":"hosi hosi","problems":[{"problem":{"name":"puskesmas","label":"puskesmas"},"tryCount":0,"pendingCount":0,"isSolved":false,"firstToSolve":false,"time":null},{"problem":{"name":"vice-sedang-prima","label":"vice-sedang-prima"},"tryCount":2,"pendingCount":0,"isSolved":true,"firstToSolve":false,"time":71},{"problem":{"name":"vice-bermain-angka","label":"vice-bermain-angka"},"tryCount":0,"pendingCount":0,"isSolved":false,"firstToSolve":false,"time":null},{"problem":{"name":"si-paling-kebo","label":"si-paling-kebo"},"tryCount":0,"pendingCount":0,"isSolved":false,"firstToSolve":false,"time":null},{"problem":{"name":"pembukaan","label":"pembukaan"},"tryCount":1,"pendingCount":0,"isSolved":true,"firstToSolve":false,"time":1197},{"problem":{"name":"sapi-betina","label":"sapi-betina"},"tryCount":3,"pendingCount":0,"isSolved":false,"firstToSolve":false,"time":null}],"score":{"penalty":1268,"solvedCount":2}},{"id":"13588321","institution":{"name":"Institut Teknologi Sepuluh Nopember"},"name":"Ligar Arsa Arnata","problems":[{"problem":{"name":"puskesmas","label":"puskesmas"},"tryCount":0,"pendingCount":0,"isSolved":false,"firstToSolve":false,"time":null},{"problem":{"name":"vice-sedang-prima","label":"vice-sedang-prima"},"tryCount":3,"pendingCount":0,"isSolved":true,"firstToSolve":false,"time":86},{"problem":{"name":"vice-bermain-angka","label":"vice-bermain-angka"},"tryCount":0,"pendingCount":0,"isSolved":false,"firstToSolve":false,"time":null},{"problem":{"name":"si-paling-kebo","label":"si-paling-kebo"},"tryCount":0,"pendingCount":0,"isSolved":false,"firstToSolve":false,"time":null},{"problem":{"name":"pembukaan","label":"pembukaan"},"tryCount":2,"pendingCount":0,"isSolved":true,"firstToSolve":false,"time":1234},{"problem":{"name":"sapi-betina","label":"sapi-betina"},"tryCount":4,"pendingCount":0,"isSolved":false,"firstToSolve":false,"time":null}],"score":{"penalty":1321,"solvedCount":2}},{"id":"13698070","institution":{"name":"Institut Teknologi Sepuluh Nopember"},"name":"Cookie Meme","problems":[{"problem":{"name":"puskesmas","label":"puskesmas"},"tryCount":0,"pendingCount":0,"isSolved":false,"firstToSolve":false,"time":null},{"problem":{"name":"vice-sedang-prima","label":"vice-sedang-prima"},"tryCount":1,"pendingCount":0,"isSolved":true,"firstToSolve":false,"time":800},{"problem":{"name":"vice-bermain-angka","label":"vice-bermain-angka"},"tryCount":0,"pendingCount":0,"isSolved":false,"firstToSolve":false,"time":null},{"problem":{"name":"si-paling-kebo","label":"si-paling-kebo"},"tryCount":0,"pendingCount":0,"isSolved":false,"firstToSolve":false,"time":null},{"problem":{"name":"pembukaan","label":"pembukaan"},"tryCount":3,"pendingCount":0,"isSolved":true,"firstToSolve":false,"time":690},{"problem":{"name":"sapi-betina","label":"sapi-betina"},"tryCount":1,"pendingCount":0,"isSolved":false,"firstToSolve":false,"time":null}],"score":{"penalty":1491,"solvedCount":2}},{"id":"13695860","institution":{"name":"Institut Teknologi Sepuluh Nopember"},"name":"naya naya","problems":[{"problem":{"name":"puskesmas","label":"puskesmas"},"tryCount":0,"pendingCount":0,"isSolved":false,"firstToSolve":false,"time":null},{"problem":{"name":"vice-sedang-prima","label":"vice-sedang-prima"},"tryCount":1,"pendingCount":0,"isSolved":true,"firstToSolve":false,"time":329},{"problem":{"name":"vice-bermain-angka","label":"vice-bermain-angka"},"tryCount":0,"pendingCount":0,"isSolved":false,"firstToSolve":false,"time":null},{"problem":{"name":"si-paling-kebo","label":"si-paling-kebo"},"tryCount":0,"pendingCount":0,"isSolved":false,"firstToSolve":false,"time":null},{"problem":{"name":"pembukaan","label":"pembukaan"},"tryCount":1,"pendingCount":0,"isSolved":true,"firstToSolve":false,"time":1431},{"problem":{"name":"sapi-betina","label":"sapi-betina"},"tryCount":0,"pendingCount":0,"isSolved":false,"firstToSolve":false,"time":null}],"score":{"penalty":1760,"solvedCount":2}},{"id":"13663317","institution":{"name":"Institut Teknologi Sepuluh Nopember"},"name":"Faizah Nurdianti","problems":[{"problem":{"name":"puskesmas","label":"puskesmas"},"tryCount":0,"pendingCount":0,"isSolved":false,"firstToSolve":false,"time":null},{"problem":{"name":"vice-sedang-prima","label":"vice-sedang-prima"},"tryCount":3,"pendingCount":0,"isSolved":true,"firstToSolve":false,"time":162},{"problem":{"name":"vice-bermain-angka","label":"vice-bermain-angka"},"tryCount":0,"pendingCount":0,"isSolved":false,"firstToSolve":false,"time":null},{"problem":{"name":"si-paling-kebo","label":"si-paling-kebo"},"tryCount":0,"pendingCount":0,"isSolved":false,"firstToSolve":false,"time":null},{"problem":{"name":"pembukaan","label":"pembukaan"},"tryCount":0,"pendingCount":0,"isSolved":false,"firstToSolve":false,"time":null},{"problem":{"name":"sapi-betina","label":"sapi-betina"},"tryCount":0,"pendingCount":0,"isSolved":false,"firstToSolve":false,"time":null}],"score":{"penalty":163,"solvedCount":1}},{"id":"13588333","institution":{"name":"Institut Teknologi Sepuluh Nopember"},"name":"Rizky Alifiyah","problems":[{"problem":{"name":"puskesmas","label":"puskesmas"},"tryCount":0,"pendingCount":0,"isSolved":false,"firstToSolve":false,"time":null},{"problem":{"name":"vice-sedang-prima","label":"vice-sedang-prima"},"tryCount":1,"pendingCount":0,"isSolved":true,"firstToSolve":false,"time":841},{"problem":{"name":"vice-bermain-angka","label":"vice-bermain-angka"},"tryCount":0,"pendingCount":0,"isSolved":false,"firstToSolve":false,"time":null},{"problem":{"name":"si-paling-kebo","label":"si-paling-kebo"},"tryCount":0,"pendingCount":0,"isSolved":false,"firstToSolve":false,"time":null},{"problem":{"name":"pembukaan","label":"pembukaan"},"tryCount":0,"pendingCount":0,"isSolved":false,"firstToSolve":false,"time":null},{"problem":{"name":"sapi-betina","label":"sapi-betina"},"tryCount":0,"pendingCount":0,"isSolved":false,"firstToSolve":false,"time":null}],"score":{"penalty":841,"solvedCount":1}},{"id":"13663323","institution":{"name":"Institut Teknologi Sepuluh Nopember"},"name":"C_5025211178_Ryan Abinugraha","problems":[{"problem":{"name":"puskesmas","label":"puskesmas"},"tryCount":0,"pendingCount":0,"isSolved":false,"firstToSolve":false,"time":null},{"problem":{"name":"vice-sedang-prima","label":"vice-sedang-prima"},"tryCount":2,"pendingCount":0,"isSolved":true,"firstToSolve":false,"time":948},{"problem":{"name":"vice-bermain-angka","label":"vice-bermain-angka"},"tryCount":0,"pendingCount":0,"isSolved":false,"firstToSolve":false,"time":null},{"problem":{"name":"si-paling-kebo","label":"si-paling-kebo"},"tryCount":0,"pendingCount":0,"isSolved":false,"firstToSolve":false,"time":null},{"problem":{"name":"pembukaan","label":"pembukaan"},"tryCount":0,"pendingCount":0,"isSolved":false,"firstToSolve":false,"time":null},{"problem":{"name":"sapi-betina","label":"sapi-betina"},"tryCount":0,"pendingCount":0,"isSolved":false,"firstToSolve":false,"time":null}],"score":{"penalty":948,"solvedCount":1}},{"id":"13588324","institution":{"name":"Institut Teknologi Sepuluh Nopember"},"name":"Aida Fitrania","problems":[{"problem":{"name":"puskesmas","label":"puskesmas"},"tryCount":0,"pendingCount":0,"isSolved":false,"firstToSolve":false,"time":null},{"problem":{"name":"vice-sedang-prima","label":"vice-sedang-prima"},"tryCount":3,"pendingCount":0,"isSolved":true,"firstToSolve":false,"time":1021},{"problem":{"name":"vice-bermain-angka","label":"vice-bermain-angka"},"tryCount":0,"pendingCount":0,"isSolved":false,"firstToSolve":false,"time":null},{"problem":{"name":"si-paling-kebo","label":"si-paling-kebo"},"tryCount":0,"pendingCount":0,"isSolved":false,"firstToSolve":false,"time":null},{"problem":{"name":"pembukaan","label":"pembukaan"},"tryCount":0,"pendingCount":0,"isSolved":false,"firstToSolve":false,"time":null},{"problem":{"name":"sapi-betina","label":"sapi-betina"},"tryCount":0,"pendingCount":0,"isSolved":false,"firstToSolve":false,"time":null}],"score":{"penalty":1021,"solvedCount":1}},{"id":"13663358","institution":{"name":"Institut Teknologi Sepuluh Nopember"},"name":"Ghifari Maaliki","problems":[{"problem":{"name":"puskesmas","label":"puskesmas"},"tryCount":0,"pendingCount":0,"isSolved":false,"firstToSolve":false,"time":null},{"problem":{"name":"vice-sedang-prima","label":"vice-sedang-prima"},"tryCount":1,"pendingCount":0,"isSolved":false,"firstToSolve":false,"time":null},{"problem":{"name":"vice-bermain-angka","label":"vice-bermain-angka"},"tryCount":0,"pendingCount":0,"isSolved":false,"firstToSolve":false,"time":null},{"problem":{"name":"si-paling-kebo","label":"si-paling-kebo"},"tryCount":0,"pendingCount":0,"isSolved":false,"firstToSolve":false,"time":null},{"problem":{"name":"pembukaan","label":"pembukaan"},"tryCount":2,"pendingCount":0,"isSolved":true,"firstToSolve":false,"time":1257},{"problem":{"name":"sapi-betina","label":"sapi-betina"},"tryCount":0,"pendingCount":0,"isSolved":false,"firstToSolve":false,"time":null}],"score":{"penalty":1257,"solvedCount":1}},{"id":"13663368","institution":{"name":"Institut Teknologi Sepuluh Nopember"},"name":"C_1184_Dimas Prihady Setyawan","problems":[{"problem":{"name":"puskesmas","label":"puskesmas"},"tryCount":0,"pendingCount":0,"isSolved":false,"firstToSolve":false,"time":null},{"problem":{"name":"vice-sedang-prima","label":"vice-sedang-prima"},"tryCount":3,"pendingCount":0,"isSolved":true,"firstToSolve":false,"time":1312},{"problem":{"name":"vice-bermain-angka","label":"vice-bermain-angka"},"tryCount":0,"pendingCount":0,"isSolved":false,"firstToSolve":false,"time":null},{"problem":{"name":"si-paling-kebo","label":"si-paling-kebo"},"tryCount":0,"pendingCount":0,"isSolved":false,"firstToSolve":false,"time":null},{"problem":{"name":"pembukaan","label":"pembukaan"},"tryCount":0,"pendingCount":0,"isSolved":false,"firstToSolve":false,"time":null},{"problem":{"name":"sapi-betina","label":"sapi-betina"},"tryCount":0,"pendingCount":0,"isSolved":false,"firstToSolve":false,"time":null}],"score":{"penalty":1312,"solvedCount":1}},{"id":"13613329","institution":{"name":"Institut Teknologi Sepuluh Nopember"},"name":"Immanuel ps","problems":[{"problem":{"name":"puskesmas","label":"puskesmas"},"tryCount":0,"pendingCount":0,"isSolved":false,"firstToSolve":false,"time":null},{"problem":{"name":"vice-sedang-prima","label":"vice-sedang-prima"},"tryCount":2,"pendingCount":0,"isSolved":true,"firstToSolve":false,"time":1351},{"problem":{"name":"vice-bermain-angka","label":"vice-bermain-angka"},"tryCount":0,"pendingCount":0,"isSolved":false,"firstToSolve":false,"time":null},{"problem":{"name":"si-paling-kebo","label":"si-paling-kebo"},"tryCount":0,"pendingCount":0,"isSolved":false,"firstToSolve":false,"time":null},{"problem":{"name":"pembukaan","label":"pembukaan"},"tryCount":0,"pendingCount":0,"isSolved":false,"firstToSolve":false,"time":null},{"problem":{"name":"sapi-betina","label":"sapi-betina"},"tryCount":0,"pendingCount":0,"isSolved":false,"firstToSolve":false,"time":null}],"score":{"penalty":1352,"solvedCount":1}},{"id":"13588341","institution":{"name":"Institut Teknologi Sepuluh Nopember"},"name":"Danno Dan","problems":[{"problem":{"name":"puskesmas","label":"puskesmas"},"tryCount":0,"pendingCount":0,"isSolved":false,"firstToSolve":false,"time":null},{"problem":{"name":"vice-sedang-prima","label":"vice-sedang-prima"},"tryCount":1,"pendingCount":0,"isSolved":true,"firstToSolve":false,"time":1386},{"problem":{"name":"vice-bermain-angka","label":"vice-bermain-angka"},"tryCount":0,"pendingCount":0,"isSolved":false,"firstToSolve":false,"time":null},{"problem":{"name":"si-paling-kebo","label":"si-paling-kebo"},"tryCount":0,"pendingCount":0,"isSolved":false,"firstToSolve":false,"time":null},{"problem":{"name":"pembukaan","label":"pembukaan"},"tryCount":0,"pendingCount":0,"isSolved":false,"firstToSolve":false,"time":null},{"problem":{"name":"sapi-betina","label":"sapi-betina"},"tryCount":0,"pendingCount":0,"isSolved":false,"firstToSolve":false,"time":null}],"score":{"penalty":1386,"solvedCount":1}},{"id":"13694129","institution":{"name":"Institut Teknologi Sepuluh Nopember"},"name":"Lihardo Marson","problems":[{"problem":{"name":"puskesmas","label":"puskesmas"},"tryCount":0,"pendingCount":0,"isSolved":false,"firstToSolve":false,"time":null},{"problem":{"name":"vice-sedang-prima","label":"vice-sedang-prima"},"tryCount":1,"pendingCount":0,"isSolved":true,"firstToSolve":false,"time":1411},{"problem":{"name":"vice-bermain-angka","label":"vice-bermain-angka"},"tryCount":0,"pendingCount":0,"isSolved":false,"firstToSolve":false,"time":null},{"problem":{"name":"si-paling-kebo","label":"si-paling-kebo"},"tryCount":0,"pendingCount":0,"isSolved":false,"firstToSolve":false,"time":null},{"problem":{"name":"pembukaan","label":"pembukaan"},"tryCount":0,"pendingCount":0,"isSolved":false,"firstToSolve":false,"time":null},{"problem":{"name":"sapi-betina","label":"sapi-betina"},"tryCount":0,"pendingCount":0,"isSolved":false,"firstToSolve":false,"time":null}],"score":{"penalty":1411,"solvedCount":1}},{"id":"13589196","institution":{"name":"Institut Teknologi Sepuluh Nopember"},"name":"Muhammad Zien Zidan","problems":[{"problem":{"name":"puskesmas","label":"puskesmas"},"tryCount":0,"pendingCount":0,"isSolved":false,"firstToSolve":false,"time":null},{"problem":{"name":"vice-sedang-prima","label":"vice-sedang-prima"},"tryCount":2,"pendingCount":0,"isSolved":true,"firstToSolve":false,"time":1417},{"problem":{"name":"vice-bermain-angka","label":"vice-bermain-angka"},"tryCount":0,"pendingCount":0,"isSolved":false,"firstToSolve":false,"time":null},{"problem":{"name":"si-paling-kebo","label":"si-paling-kebo"},"tryCount":0,"pendingCount":0,"isSolved":false,"firstToSolve":false,"time":null},{"problem":{"name":"pembukaan","label":"pembukaan"},"tryCount":0,"pendingCount":0,"isSolved":false,"firstToSolve":false,"time":null},{"problem":{"name":"sapi-betina","label":"sapi-betina"},"tryCount":0,"pendingCount":0,"isSolved":false,"firstToSolve":false,"time":null}],"score":{"penalty":1417,"solvedCount":1}},{"id":"13547854","institution":{"name":"Institut Teknologi Sepuluh Nopember"},"name":"Sandyatama Fransisna","problems":[{"problem":{"name":"puskesmas","label":"puskesmas"},"tryCount":0,"pendingCount":0,"isSolved":false,"firstToSolve":false,"time":null},{"problem":{"name":"vice-sedang-prima","label":"vice-sedang-prima"},"tryCount":3,"pendingCount":0,"isSolved":true,"firstToSolve":false,"time":1438},{"problem":{"name":"vice-bermain-angka","label":"vice-bermain-angka"},"tryCount":0,"pendingCount":0,"isSolved":false,"firstToSolve":false,"time":null},{"problem":{"name":"si-paling-kebo","label":"si-paling-kebo"},"tryCount":0,"pendingCount":0,"isSolved":false,"firstToSolve":false,"time":null},{"problem":{"name":"pembukaan","label":"pembukaan"},"tryCount":0,"pendingCount":0,"isSolved":false,"firstToSolve":false,"time":null},{"problem":{"name":"sapi-betina","label":"sapi-betina"},"tryCount":0,"pendingCount":0,"isSolved":false,"firstToSolve":false,"time":null}],"score":{"penalty":1439,"solvedCount":1}},{"id":"13663690","institution":{"name":"Institut Teknologi Sepuluh Nopember"},"name":"Fauzi Rizki Pratama","problems":[{"problem":{"name":"puskesmas","label":"puskesmas"},"tryCount":0,"pendingCount":0,"isSolved":false,"firstToSolve":false,"time":null},{"problem":{"name":"vice-sedang-prima","label":"vice-sedang-prima"},"tryCount":1,"pendingCount":0,"isSolved":false,"firstToSolve":false,"time":null},{"problem":{"name":"vice-bermain-angka","label":"vice-bermain-angka"},"tryCount":0,"pendingCount":0,"isSolved":false,"firstToSolve":false,"time":null},{"problem":{"name":"si-paling-kebo","label":"si-paling-kebo"},"tryCount":0,"pendingCount":0,"isSolved":false,"firstToSolve":false,"time":null},{"problem":{"name":"pembukaan","label":"pembukaan"},"tryCount":0,"pendingCount":0,"isSolved":false,"firstToSolve":false,"time":null},{"problem":{"name":"sapi-betina","label":"sapi-betina"},"tryCount":0,"pendingCount":0,"isSolved":false,"firstToSolve":false,"time":null}],"score":{"penalty":0,"solvedCount":0}},{"id":"13598414","institution":{"name":"Institut Teknologi Sepuluh Nopember"},"name":"Salsabila Fatma Aripa","problems":[{"problem":{"name":"puskesmas","label":"puskesmas"},"tryCount":0,"pendingCount":0,"isSolved":false,"firstToSolve":false,"time":null},{"problem":{"name":"vice-sedang-prima","label":"vice-sedang-prima"},"tryCount":1,"pendingCount":0,"isSolved":false,"firstToSolve":false,"time":null},{"problem":{"name":"vice-bermain-angka","label":"vice-bermain-angka"},"tryCount":0,"pendingCount":0,"isSolved":false,"firstToSolve":false,"time":null},{"problem":{"name":"si-paling-kebo","label":"si-paling-kebo"},"tryCount":0,"pendingCount":0,"isSolved":false,"firstToSolve":false,"time":null},{"problem":{"name":"pembukaan","label":"pembukaan"},"tryCount":0,"pendingCount":0,"isSolved":false,"firstToSolve":false,"time":null},{"problem":{"name":"sapi-betina","label":"sapi-betina"},"tryCount":0,"pendingCount":0,"isSolved":false,"firstToSolve":false,"time":null}],"score":{"penalty":0,"solvedCount":0}},{"id":"13703481","institution":{"name":"Institut Teknologi Sepuluh Nopember"},"name":"Kartika Diva Asmara Gita","problems":[{"problem":{"name":"puskesmas","label":"puskesmas"},"tryCount":0,"pendingCount":0,"isSolved":false,"firstToSolve":false,"time":null},{"problem":{"name":"vice-sedang-prima","label":"vice-sedang-prima"},"tryCount":2,"pendingCount":0,"isSolved":false,"firstToSolve":false,"time":null},{"problem":{"name":"vice-bermain-angka","label":"vice-bermain-angka"},"tryCount":0,"pendingCount":0,"isSolved":false,"firstToSolve":false,"time":null},{"problem":{"name":"si-paling-kebo","label":"si-paling-kebo"},"tryCount":0,"pendingCount":0,"isSolved":false,"firstToSolve":false,"time":null},{"problem":{"name":"pembukaan","label":"pembukaan"},"tryCount":0,"pendingCount":0,"isSolved":false,"firstToSolve":false,"time":null},{"problem":{"name":"sapi-betina","label":"sapi-betina"},"tryCount":0,"pendingCount":0,"isSolved":false,"firstToSolve":false,"time":null}],"score":{"penalty":0,"solvedCount":0}}]},"lastUpdated":"3/4/2022 2.05.07 AM"}